culendar/__init__.py
culendar/__main__.py
culendar/calendar.py
culendar/config.py
culendar/confscr.py
culendar/culdav.py
culendar/culendar.py
culendar/helpscr.py
culendar/i18n.py
culendar/inputs.py
culendar/locale/fr/LC_MESSAGES/culendar.mo
culendar/locale/fr/LC_MESSAGES/culendar.po.backup
culendar/locale/fr/LC_MESSAGES/culendar.pot
culendar/locale/fr/LC_MESSAGES/new.pot
culendar/patch
culendar/ui.py
culendar-0.20251111.dist-info/LICENSE
culendar-0.20251111.dist-info/METADATA
culendar-0.20251111.dist-info/WHEEL
culendar-0.20251111.dist-info/entry_points.txt
culendar-0.20251111.dist-info/RECORD
