Metadata-Version: 2.3
Name: culendar
Version: 0.20251111
Summary: Culendar is a free/libre calendar application in python and curses.
License: WTFPL
Keywords: calendar,curses,console
Author: Mit
Author-email: culendar@miteux.net
Maintainer: Mit
Maintainer-email: culendar@miteux.net
Requires-Python: >=3.9
Classifier: Development Status :: 3 - Alpha
Classifier: Environment :: Console :: Curses
Classifier: Intended Audience :: End Users/Desktop
Classifier: License :: Other/Proprietary License
Classifier: License :: Public Domain
Classifier: Operating System :: OS Independent
Classifier: Programming Language :: Python :: 3
Classifier: Programming Language :: Python :: 3.9
Classifier: Programming Language :: Python :: 3.10
Classifier: Programming Language :: Python :: 3.11
Classifier: Programming Language :: Python :: 3.12
Classifier: Programming Language :: Python :: 3.13
Classifier: Topic :: Utilities
Classifier: Typing :: Typed
Requires-Dist: caldav (>=1.2.1)
Requires-Dist: icalendar (>=5.0.4)
Project-URL: Bug Tracker, https://framagit.org/mit/culendar/-/issues
Project-URL: Homepage, https://framagit.org/mit/culendar
Project-URL: Merge Requests, https://framagit.org/mit/culendar/-/merge_requests
Project-URL: Repository, https://framagit.org/mit/culendar
